<annotation>
	<folder>combined</folder>
	<filename>pokemon-12.jpg</filename>
	<path>/home/ares/Work/xa/pokemon_project/data/data/combined/pokemon-12.jpg</path>
	<source>
		<database>Unknown</database>
	</source>
	<size>
		<width>487</width>
		<height>600</height>
		<depth>3</depth>
	</size>
	<segmented>0</segmented>
	<object>
		<name>charmander</name>
		<pose>Unspecified</pose>
		<truncated>0</truncated>
		<difficult>0</difficult>
		<bndbox>
			<xmin>15</xmin>
			<ymin>110</ymin>
			<xmax>468</xmax>
			<ymax>541</ymax>
		</bndbox>
	</object>
</annotation>